pytitle/__init__.py
pytitle/logger.py
pytitle/ass/__init__.py
pytitle/srt/__init__.py
pytitle/srt/exceptions.py
pytitle/srt/regex.py
pytitle/srt/subtitle.py
pytitle/srt/types.py
pytitle/vtt/__init__.py
pytitle-0.1.6.dist-info/LICENSE
pytitle-0.1.6.dist-info/METADATA
pytitle-0.1.6.dist-info/WHEEL
pytitle-0.1.6.dist-info/top_level.txt
pytitle-0.1.6.dist-info/RECORD
