Metadata-Version: 2.1
Name: pytitle
Version: 0.1.6
Summary: Subtitle manipulation library for python.
Home-page: https://github.com/sina-e/pytitle
Author: Sina Ebrahimi
Author-email: ebrahimisina78@gmail.com
License: MIT
Project-URL: Documentation, https://pytitle.readthedocs.io
Project-URL: Source, https://github.com/sina-e/pytitle
Keywords: subtitle,subtitles,subtitle-manipulation,subtitle-manipulation-library,subtitle-manipulation-python,srt-subtitles,vtt-subtitles,ssa-subtitles,ass-subtitles,srt,vtt,ass,ssa,subtitle-edit,subtitle-editor
Platform: UNKNOWN
Classifier: Development Status :: 2 - Pre-Alpha
Classifier: Environment :: Console
Classifier: Intended Audience :: Developers
Classifier: License :: OSI Approved :: MIT License
Classifier: Programming Language :: Python
Classifier: Programming Language :: Python :: 3.8
Classifier: Programming Language :: Python :: 3.9
Classifier: Programming Language :: Python :: 3.10
Classifier: Topic :: Multimedia :: Video
Classifier: Topic :: Software Development :: Libraries
Classifier: Topic :: Software Development :: Libraries :: Application Frameworks
Classifier: Topic :: Software Development :: Libraries :: Python Modules
Classifier: Topic :: Text Processing
Classifier: Typing :: Typed
Requires-Python: >=3.8
License-File: LICENSE
Requires-Dist: pydantic (>=1.9.0)
